LICENSE
MANIFEST.in
README.md
setup.py
src/pysproto/msvcint.h
src/pysproto/python_sproto.c
src/pysproto/sproto.c
src/pysproto/sproto.h
src/pysproto.egg-info/PKG-INFO
src/pysproto.egg-info/SOURCES.txt
src/pysproto.egg-info/dependency_links.txt
src/pysproto.egg-info/top_level.txt
src/pysproto_rpc/__init__.py
src/pysproto_rpc/sproto.py
test/test.py
test/test_dict_nested_memleak.py
test/test_mem.py
test/test_wild_pointer.py