Metadata-Version: 2.1
Name: pysproto
Version: 0.1.9
Summary: python binding to sproto, a serialize library
Home-page: http://github.com/spin6lock/python-sproto
Author: spin6lock
Author-email: UNKNOWN
License: MIT
Keywords: sproto,serialization
Requires-Python: >=3.6
License-File: LICENSE
